tests/__init__.py
tests/test.py
tests/test2.py
tests/test3.py
tests/test_agent_response_transformer.py
tests/test_single_claude_json_to_openai_response.py
agent_response_transformer-0.1.2.dist-info/METADATA
agent_response_transformer-0.1.2.dist-info/WHEEL
agent_response_transformer-0.1.2.dist-info/top_level.txt
agent_response_transformer-0.1.2.dist-info/RECORD
