Metadata-Version: 2.4
Name: agent-response-transformer
Version: 0.1.2
Summary: A Python SDK to transform Claude response to OpenAI response format
Home-page: https://github.com/protagolabs/agent-response-transformer
Author: yi.zhou
Author-email: yi.zhou@netmind.ai
Classifier: Development Status :: 4 - Beta
Classifier: Intended Audience :: Developers
Classifier: License :: OSI Approved :: MIT License
Classifier: Operating System :: OS Independent
Classifier: Programming Language :: Python :: 3
Classifier: Programming Language :: Python :: 3.7
Classifier: Programming Language :: Python :: 3.8
Classifier: Programming Language :: Python :: 3.9
Classifier: Programming Language :: Python :: 3.10
Classifier: Programming Language :: Python :: 3.11
Requires-Python: >=3.7
Requires-Dist: openai
Requires-Dist: openai-agents
Dynamic: author
Dynamic: author-email
Dynamic: classifier
Dynamic: description
Dynamic: description-content-type
Dynamic: home-page
Dynamic: requires-dist
Dynamic: requires-python
Dynamic: summary
